PyIPAM-0.1.4.dist-info/DESCRIPTION.rst
PyIPAM-0.1.4.dist-info/METADATA
PyIPAM-0.1.4.dist-info/RECORD
PyIPAM-0.1.4.dist-info/WHEEL
PyIPAM-0.1.4.dist-info/entry_points.txt
PyIPAM-0.1.4.dist-info/metadata.json
PyIPAM-0.1.4.dist-info/top_level.txt
pyipam/__init__.py
pyipam/server.py
pyipam/classes/__init__.py
pyipam/classes/background.py
pyipam/classes/config.py
pyipam/classes/db.py
pyipam/config/main.ini.example
pyipam/controllers/__init__.py
pyipam/controllers/main.py
pyipam/controllers/subnets.py
pyipam/models/__init__.py
pyipam/models/main.py
pyipam/models/subnets.py
pyipam/static/css/alerts.css
pyipam/static/css/forms.css
pyipam/static/css/main.css
pyipam/static/css/table.css
pyipam/static/img/GitHub-Mark-Light-32px.png
pyipam/static/img/icons8-networking-manager-100.png
pyipam/static/js/ip_check.js
pyipam/static/js/ip_edit.js
pyipam/static/js/ip_table_nav.js
pyipam/static/js/search.js
pyipam/templates/layout.html
pyipam/templates/main/about.html
pyipam/templates/main/error.html
pyipam/templates/main/home.html
pyipam/templates/main/info.html
pyipam/templates/main/setup.html
pyipam/templates/subnet/form.html
pyipam/templates/subnet/view.html
