Metadata-Version: 2.0
Name: PyIPAM
Version: 0.1.4
Summary: The Simple Python Flask IP Address Manager
Home-page: https://github.com/marknet15/pyipam
Author: Mark Woolley
Author-email: mw@marknet15.com
License: MIT
Platform: UNKNOWN
Classifier: Development Status :: 3 - Alpha
Classifier: Intended Audience :: System Administrators
Classifier: License :: OSI Approved :: MIT License
Classifier: Programming Language :: Python :: 3
Requires-Dist: flask
Requires-Dist: waitress
Requires-Dist: psycopg2-binary
Requires-Dist: ipaddress
Requires-Dist: configparser
